uikitty/__init__.py
uikitty/base_selector.py
uikitty/dynamic_selector.py
uikitty/functions.py
uikitty/paginator.py
bot_ui_kitty-0.1.5.dist-info/LICENSE
bot_ui_kitty-0.1.5.dist-info/METADATA
bot_ui_kitty-0.1.5.dist-info/WHEEL
bot_ui_kitty-0.1.5.dist-info/top_level.txt
bot_ui_kitty-0.1.5.dist-info/RECORD
