Metadata-Version: 2.1
Name: bot-ui-kitty
Version: 0.1.5
Summary: A UI kit containing reusable, dynamic, and intuitive views for Discord bots.
Home-page: https://github.com/nuztalgia/bot-ui-kitty
Author: Nuztalgia
Author-email: nuztalgia@gmail.com
License: Apache-2.0
Project-URL: Issue Tracker, https://github.com/nuztalgia/bot-ui-kitty/issues
Project-URL: Source Code, https://github.com/nuztalgia/bot-ui-kitty/tree/main/uikitty
Keywords: bot,components,discord,kitty,ui,ui kit,utilities,views
Classifier: Development Status :: 4 - Beta
Classifier: Intended Audience :: Developers
Classifier: License :: OSI Approved :: Apache Software License
Classifier: Natural Language :: English
Classifier: Operating System :: OS Independent
Classifier: Programming Language :: Python :: 3 :: Only
Classifier: Programming Language :: Python :: 3.10
Classifier: Programming Language :: Python :: 3.11
Classifier: Topic :: Communications :: Chat
Classifier: Topic :: Software Development :: Libraries :: Python Modules
Classifier: Topic :: Utilities
Classifier: Typing :: Typed
Requires-Python: >=3.10
License-File: LICENSE
Requires-Dist: py-cord (==2.3.2)
